pywireguard/__init__.py
pywireguard/factory.py
pywireguard/base/__init__.py
pywireguard/base/exceptions.py
pywireguard/base/interface.py
pywireguard/base/peer.py
pywireguard/base/utils.py
pywireguard/base/cli/__init__.py
pywireguard/base/cli/interface.py
pywireguard/base/cli/peer.py
pywireguard/base/darwin/__init__.py
pywireguard/base/darwin/interface.py
pywireguard/base/linux/__init__.py
pywireguard/base/linux/interface.py
pywireguard/base/linux/peer.py
pywireguard/base/userspace/__init__.py
pywireguard/base/userspace/interface.py
pywireguard/base/userspace/peer.py
pywireguard/base/windows/__init__.py
pywireguard/base/windows/interface.py
pywireguard-2.2.3.dist-info/LICENSE
pywireguard-2.2.3.dist-info/METADATA
pywireguard-2.2.3.dist-info/WHEEL
pywireguard-2.2.3.dist-info/top_level.txt
pywireguard-2.2.3.dist-info/RECORD
